Workbook

Sheet Listas
A1: Categorias | B1: Usuarios
A2: Alimentación | B2: admin
A3: Transporte | B3: pareja
A4: Servicios
A5: Vivienda/alquiler
A6: Salud
A7: Entretenimiento
A8: Cuidado personal
A9: Educación
A10: Deudas/pagos
A11: Mascotas
A12: Otros
A13: Sueldo/salario
A14: Freelance/ingresos extra
A15: Regalos/ayudas

Sheet Movimientos
A1: id | B1: fecha | C1: usuario | D1: tipo | E1: categoria | F1: monto_bs | G1: tasa_bcv_dia | H1: monto_usd | I1: nota | J1: timestamp_registro | L1: id/tasa_bcv_dia/monto_usd/timestamp_registro los llena Apps Script automáticamente
A2: ejemplo-no-borrar | B2: 2026-07-17 | C2: admin | D2: gasto | E2: Alimentación | F2: 450 | G2: 200 | H2: 2.25 | I2: Ejemplo de formato — puedes borrar esta fila | J2: 2026-07-17 10:00:00

Sheet Deudas
A1: id | B1: descripcion | C1: monto_original | D1: moneda | E1: saldo_pendiente | F1: fecha_vencimiento | G1: estado | H1: usuario_responsable
A2: ejemplo-no-borrar | B2: Ejemplo: préstamo carro | C2: 5000 | D2: USD | E2: 3500 | F2: 2027-01-15 | G2: pendiente | H2: admin

Sheet Tasas_Cambio
A1: fecha | B1: tasa_bcv | D1: Hoja administrada automáticamente por Apps Script (caché diario de la tasa BCV)

Sheet Usuarios
A1: usuario_id | B1: nombre | C1: rol | D1: pin_acceso | F1: Cambia los PIN de ejemplo antes de usar la app
A2: admin | B2: Admin | C2: admin | D2: 1234
A3: pareja | B3: Pareja | C3: pareja | D3: 5678

Sheet Conversiones_USDT
A1: id | B1: fecha | C1: monto_usdt | D1: tasa_usdt_bs | E1: monto_bs_resultante | F1: plataforma | G1: origen_fondos | H1: nota | J1: Tu libro de cambio manual — distinto de la tasa BCV oficial
A2: ejemplo-no-borrar | B2: 2026-07-17 | C2: 100 | D2: 220 | E2: =C2*D2 | F2: Binance | G2: Banesco Panamá | H2: Ejemplo de formato — puedes borrar esta fila

Sheet Push_Subscripciones
A1: endpoint | B1: p256dh | C1: auth | D1: usuario_id | E1: fecha_registro | G1: Hoja administrada automáticamente por Apps Script (suscripciones Web Push)

Sheet Resumen
A1: Resumen consolidado (solo admin)
A3: Totales por usuario
A4: Usuario | B4: Gastos (Bs) | C4: Ingresos (Bs) | D4: Balance (Bs) | E4: Balance (USD)
A5: admin | B5: =SUMIFS(Movimientos!$F:$F,Movimientos!$C:$C,"admin",Movimientos!$D:$D,"gasto") | C5: =SUMIFS(Movimientos!$F:$F,Movimientos!$C:$C,"admin",Movimientos!$D:$D,"ingreso") | D5: =C5-B5 | E5: =SUMIFS(Movimientos!$H:$H,Movimientos!$C:$C,"admin",Movimientos!$D:$D,"ingreso")-SUMIFS(Movimientos!$H:$H,Movimientos!$C:$C,"admin",Movimientos!$D:$D,"gasto")
A6: pareja | B6: =SUMIFS(Movimientos!$F:$F,Movimientos!$C:$C,"pareja",Movimientos!$D:$D,"gasto") | C6: =SUMIFS(Movimientos!$F:$F,Movimientos!$C:$C,"pareja",Movimientos!$D:$D,"ingreso") | D6: =C6-B6 | E6: =SUMIFS(Movimientos!$H:$H,Movimientos!$C:$C,"pareja",Movimientos!$D:$D,"ingreso")-SUMIFS(Movimientos!$H:$H,Movimientos!$C:$C,"pareja",Movimientos!$D:$D,"gasto")
A8: Balance general
A9: Total ingresos (Bs) | B9: =SUMIFS(Movimientos!$F:$F,Movimientos!$D:$D,"ingreso")
A10: Total gastos (Bs) | B10: =SUMIFS(Movimientos!$F:$F,Movimientos!$D:$D,"gasto")
A11: Balance neto (Bs) | B11: =B9-B10
A13: Gastos por categoría (Bs)
A14: Categoría | B14: Total (Bs)
A15: Alimentación | B15: =SUMIFS(Movimientos!$F:$F,Movimientos!$D:$D,"gasto",Movimientos!$E:$E,"Alimentación")
A16: Transporte | B16: =SUMIFS(Movimientos!$F:$F,Movimientos!$D:$D,"gasto",Movimientos!$E:$E,"Transporte")
A17: Servicios | B17: =SUMIFS(Movimientos!$F:$F,Movimientos!$D:$D,"gasto",Movimientos!$E:$E,"Servicios")
A18: Vivienda/alquiler | B18: =SUMIFS(Movimientos!$F:$F,Movimientos!$D:$D,"gasto",Movimientos!$E:$E,"Vivienda/alquiler")
A19: Salud | B19: =SUMIFS(Movimientos!$F:$F,Movimientos!$D:$D,"gasto",Movimientos!$E:$E,"Salud")
A20: Entretenimiento | B20: =SUMIFS(Movimientos!$F:$F,Movimientos!$D:$D,"gasto",Movimientos!$E:$E,"Entretenimiento")
A21: Cuidado personal | B21: =SUMIFS(Movimientos!$F:$F,Movimientos!$D:$D,"gasto",Movimientos!$E:$E,"Cuidado personal")
A22: Educación | B22: =SUMIFS(Movimientos!$F:$F,Movimientos!$D:$D,"gasto",Movimientos!$E:$E,"Educación")
A23: Deudas/pagos | B23: =SUMIFS(Movimientos!$F:$F,Movimientos!$D:$D,"gasto",Movimientos!$E:$E,"Deudas/pagos")
A24: Mascotas | B24: =SUMIFS(Movimientos!$F:$F,Movimientos!$D:$D,"gasto",Movimientos!$E:$E,"Mascotas")
A25: Otros | B25: =SUMIFS(Movimientos!$F:$F,Movimientos!$D:$D,"gasto",Movimientos!$E:$E,"Otros")
A27: Estado de deudas
A28: Estado | B28: Cantidad
A29: pendiente | B29: =COUNTIF(Deudas!$G:$G,"pendiente")
A30: pagada | B30: =COUNTIF(Deudas!$G:$G,"pagada")
A31: vencida | B31: =COUNTIF(Deudas!$G:$G,"vencida")
A32: parcial | B32: =COUNTIF(Deudas!$G:$G,"parcial")
A34: Saldo pendiente total (Bs) | B34: =SUMIFS(Deudas!$E:$E,Deudas!$D:$D,"Bs",Deudas!$G:$G,"pendiente")
A35: Saldo pendiente total (USD) | B35: =SUMIFS(Deudas!$E:$E,Deudas!$D:$D,"USD",Deudas!$G:$G,"pendiente")
A37: Tasa BCV vs. tu tasa real USDT→Bs (referencial)
A38: Tasa BCV más reciente | B38: =IFERROR(INDEX(Tasas_Cambio!$B:$B,MATCH(MAX(Tasas_Cambio!$A:$A),Tasas_Cambio!$A:$A,0)),"-")
A39: Tu tasa USDT→Bs promedio | B39: =IFERROR(AVERAGE(Conversiones_USDT!$D:$D),"-")
